setup.py
gaussian_binomial_probability_distribution/Binomialdistribution.py
gaussian_binomial_probability_distribution/Gaussiandistribution.py
gaussian_binomial_probability_distribution/Generaldistribution.py
gaussian_binomial_probability_distribution/__init__.py
gaussian_binomial_probability_distribution.egg-info/PKG-INFO
gaussian_binomial_probability_distribution.egg-info/SOURCES.txt
gaussian_binomial_probability_distribution.egg-info/dependency_links.txt
gaussian_binomial_probability_distribution.egg-info/not-zip-safe
gaussian_binomial_probability_distribution.egg-info/top_level.txt