Metadata-Version: 1.0
Name: gaussian-binomial-probability-distribution
Version: 0.1
Summary: Gaussian and Binomial distribution
Home-page: UNKNOWN
Author: Yittyn Ng
Author-email: ngyittyn980518@gmail.com
License: UNKNOWN
Platform: UNKNOWN
